pyPantry/__init__.py
pyPantry/utils.py
pyPantry/Algo/__init__.py
pyPantry/Algo/Sorting/Py3WayMergeSort.py
pyPantry/Algo/Sorting/PyBIngoSort.py
pyPantry/Algo/Sorting/PyBitonicSort.py
pyPantry/Algo/Sorting/PyBogoSort.py
pyPantry/Algo/Sorting/PyBubbleSort.py
pyPantry/Algo/Sorting/PyBucketSort.py
pyPantry/Algo/Sorting/PyCocktailSort.py
pyPantry/Algo/Sorting/PyCombSort.py
pyPantry/Algo/Sorting/PyCountingSort.py
pyPantry/Algo/Sorting/PyCycleSort.py
pyPantry/Algo/Sorting/PyGnomeSort.py
pyPantry/Algo/Sorting/PyHeapSort.py
pyPantry/Algo/Sorting/PyInsertionSort.py
pyPantry/Algo/Sorting/PyMergeSort.py
pyPantry/Algo/Sorting/PyOddEvenSort.py
pyPantry/Algo/Sorting/PyPancakeSort.py
pyPantry/Algo/Sorting/PyPigeonholeSort.py
pyPantry/Algo/Sorting/PyQuickSort.py
pyPantry/Algo/Sorting/PyRadixSort.py
pyPantry/Algo/Sorting/PySelectionSort.py
pyPantry/Algo/Sorting/PyShellSort.py
pyPantry/Algo/Sorting/PySleepSort.py
pyPantry/Algo/Sorting/PyStoogeSort.py
pyPantry/Algo/Sorting/PyStrandSort.py
pyPantry/Algo/Sorting/PyTagSort.py
pyPantry/Algo/Sorting/PyTimSort.py
pyPantry/Algo/Sorting/PyTreeSort.py
pyPantry/Algo/Sorting/__init__.py
pyPantry/DS/__init__.py
pyPantry/DS/Graph/PyGraph.py
pyPantry/DS/Graph/PyLinkedGraph.py
pyPantry/DS/Graph/__init__.py
pyPantry/DS/Heap/PyMaxHeap.py
pyPantry/DS/Heap/PyMinHeap.py
pyPantry/DS/Heap/__init__.py
pyPantry/DS/LinkedList/PyCircularLinkedList.py
pyPantry/DS/LinkedList/PyDoublyCircularLinkedLIst.py
pyPantry/DS/LinkedList/PyDoublyLinkedList.py
pyPantry/DS/LinkedList/PyHeaderLinkedList.py
pyPantry/DS/LinkedList/PyLinkedList.py
pyPantry/DS/LinkedList/PySkipLinkedList.py
pyPantry/DS/LinkedList/__init__.py
pyPantry/DS/Queue/PyCircularQueue.py
pyPantry/DS/Queue/PyDeque.py
pyPantry/DS/Queue/PyPriorityQueue.py
pyPantry/DS/Queue/PyQueue.py
pyPantry/DS/Queue/__init__.py
pyPantry/DS/Stack/PyStack.py
pyPantry/DS/Stack/__init__.py
pyPantry/DS/Stack/pyLinkedStack.py
pyPantry/DS/Tree/PyAVLTree.py
pyPantry/DS/Tree/PyBTree.py
pyPantry/DS/Tree/PyBinarySearchTree.py
python_Pantry-3.0.2.dist-info/LICENSE
python_Pantry-3.0.2.dist-info/METADATA
python_Pantry-3.0.2.dist-info/WHEEL
python_Pantry-3.0.2.dist-info/top_level.txt
python_Pantry-3.0.2.dist-info/RECORD
