Metadata-Version: 2.1
Name: python-Pantry
Version: 3.0.2
Summary: Python Package for Data structure and algorithms implementation with its proper explanation
Home-page: https://github.com/sattyamjjain/pyPantry
Author: Sattyam Jain
Author-email: sattyamjain96@gmail.com
Project-URL: Bug Reports, https://github.com/sattyamjjain/pyPantry
Project-URL: Source, https://github.com/sattyamjjain/pyPantry
Keywords: pydsa,pyPantry,dsa,data structure,algo,algorithm,ds,python data structure
Classifier: Development Status :: 3 - Alpha
Classifier: Intended Audience :: Developers
Classifier: License :: OSI Approved :: MIT License
Classifier: Programming Language :: Python :: 3.9
Requires-Python: >=3.9
License-File: LICENSE
Requires-Dist: black
Requires-Dist: flask
Requires-Dist: requests
